{
  "key": "kanfeihem",
  "language": "hebrew",
  "root": "kenaf",
  "occurrences": [
    {
      "location": {
        "book": "Ezekiel",
        "chapter": 1,
        "verse": 8
      },
      "wordIndex": 3,
      "word": {
        "originalScript": "כַּנְפֵיהֶם",
        "transliteration": "kanfeihem",
        "englishLiteral": "wings-their",
        "englishNatural": "their wings",
        "root": "kenaf",
        "morphology": {
          "type": "noun"
        }
      },
      "context": {
        "hebrew": "אָדָם מִתַּחַת **כַּנְפֵיהֶם** עַל אַרְבַּעַת",
        "transliteration": "Adam miTachat **kanfeihem** al arbaat",
        "englishLiteral": "Earthling (Adam) from-under **wings-their** over four-of",
        "englishNatural": "Earthling (Adam) from under **their wings** over four of"
      }
    },
    {
      "location": {
        "book": "Ezekiel",
        "chapter": 1,
        "verse": 9
      },
      "wordIndex": 4,
      "word": {
        "originalScript": "כַּנְפֵיהֶם",
        "transliteration": "kanfeihem",
        "englishLiteral": "wings-their",
        "englishNatural": "their wings",
        "root": "kenaf",
        "morphology": {
          "type": "noun"
        }
      },
      "context": {
        "hebrew": "אֶל־ אֲחוֹתָהּ **כַּנְפֵיהֶם** לֹא־ יִסַּבּוּ",
        "transliteration": "el- achotah **kanfeihem** lo- yisabbu",
        "englishLiteral": "to- sister-her **wings-their** not- they-went_around",
        "englishNatural": "to her sister **their wings** not they went-around"
      }
    },
    {
      "location": {
        "book": "Ezekiel",
        "chapter": 1,
        "verse": 23
      },
      "wordIndex": 2,
      "word": {
        "originalScript": "כַּנְפֵיהֶם",
        "transliteration": "kanfeihem",
        "englishLiteral": "wings-their",
        "englishNatural": "their wings",
        "root": "kenaf",
        "morphology": {
          "type": "noun"
        }
      },
      "context": {
        "hebrew": "וְתַחַת הָרָקִיעַ **כַּנְפֵיהֶם** יְשָׁרוֹת אִשָּׁה",
        "transliteration": "veTachat haRaqia **kanfeihem** yesharot ishah",
        "englishLiteral": "And-under the-hammering_out **wings-their** straight woman",
        "englishNatural": "And under the hammering-out **their wings** straight woman"
      }
    },
    {
      "location": {
        "book": "Ezekiel",
        "chapter": 1,
        "verse": 24
      },
      "wordIndex": 3,
      "word": {
        "originalScript": "כַּנְפֵיהֶם",
        "transliteration": "kanfeihem",
        "englishLiteral": "wings-their",
        "englishNatural": "their wings",
        "root": "kenaf",
        "morphology": {
          "type": "noun"
        }
      },
      "context": {
        "hebrew": "אֶת־ קוֹל **כַּנְפֵיהֶם** כְּקוֹל מַיִם",
        "transliteration": "et- qol **kanfeihem** keQol mayim",
        "englishLiteral": "↳ voice-of **wings-their** like-voice-of waters",
        "englishNatural": "↳ the voice of **their wings** like the voice of waters"
      }
    }
  ]
}