{
  "key": "miqadmei",
  "language": "hebrew",
  "root": "qedem",
  "occurrences": [
    {
      "location": {
        "book": "Proverbs",
        "chapter": 8,
        "verse": 23
      },
      "wordIndex": 3,
      "sourceOrder": 3,
      "word": {
        "originalScript": "מִקַּדְמֵי־",
        "transliteration": "miQadmei",
        "englishLiteral": "from-east-of",
        "englishNatural": "from the-east of",
        "root": "qedem",
        "morphology": {
          "type": "adverb"
        }
      },
      "context": {
        "hebrew": "נִסַּכְתִּי מֵרֹאשׁ **מִקַּדְמֵי־** אָרֶץ",
        "transliteration": "nisakhti meRosh **miQadmei** aretz",
        "englishLiteral": "was-poured_out-I, from-heading, **from-east-of** land.",
        "englishNatural": "I was poured-out, from the heading, **from the-east of** land."
      }
    }
  ]
}