{
  "key": "raiti",
  "language": "hebrew",
  "root": "raah",
  "occurrences": [
    {
      "location": {
        "book": "Exodus",
        "chapter": 3,
        "verse": 7
      },
      "wordIndex": 3,
      "sourceOrder": 3,
      "word": {
        "originalScript": "רָאִיתִי",
        "transliteration": "raiti",
        "englishLiteral": "I-see",
        "englishNatural": "I have seen",
        "root": "raah",
        "morphology": {
          "type": "verb",
          "tense": "perfect",
          "stem": "qal"
        }
      },
      "context": {
        "hebrew": "יְהוָה רָאֹה **רָאִיתִי** אֶת־ עֳנִי",
        "transliteration": "YHWH raoh **raiti** et- oni",
        "englishLiteral": "He_Who_Is (YHWH) \"seeing **I-see** ↳ affliction-of",
        "englishNatural": "said, \"Seeing, **I have seen** ↳ the affliction of"
      }
    },
    {
      "location": {
        "book": "Ezekiel",
        "chapter": 1,
        "verse": 27
      },
      "wordIndex": 14,
      "sourceOrder": 14,
      "word": {
        "originalScript": "רָאִיתִי",
        "transliteration": "raiti",
        "englishLiteral": "I-saw",
        "englishNatural": "I saw",
        "root": "raah",
        "morphology": {
          "type": "verb",
          "tense": "perfect",
          "stem": "qal"
        }
      },
      "context": {
        "hebrew": "מָתְנָיו וּלְמַטָּה **רָאִיתִי** כְּמַרְאֵה־ אֵשׁ",
        "transliteration": "matnav uleMattah **raiti** keMareeh- esh",
        "englishLiteral": "loins-his and-to-downward **I-saw** like-appearance-of- fire,",
        "englishNatural": "his loins and downward **I saw** like an appearance of fire,"
      }
    }
  ]
}