{
  "key": "umeat",
  "language": "hebrew",
  "root": "meah",
  "occurrences": [
    {
      "location": {
        "book": "Genesis",
        "chapter": 5,
        "verse": 3
      },
      "wordIndex": 3,
      "sourceOrder": 3,
      "word": {
        "originalScript": "וּמְאַת",
        "transliteration": "uMeat",
        "englishLiteral": "and-hundred",
        "englishNatural": "and a hundred",
        "root": "meah",
        "morphology": {
          "type": "numeral"
        }
      },
      "context": {
        "hebrew": "אָדָם שְׁלֹשִׁים **וּמְאַת** שָׁנָה וַיּוֹלֶד",
        "transliteration": "Adam shloshim **uMeat** shanah vaYoled",
        "englishLiteral": "Earthling (Adam) thirty **and-hundred** year, and-birthed",
        "englishNatural": "lived thirty **and a hundred** years, and birthed"
      }
    },
    {
      "location": {
        "book": "Genesis",
        "chapter": 5,
        "verse": 6
      },
      "wordIndex": 4,
      "sourceOrder": 4,
      "word": {
        "originalScript": "וּמְאַת",
        "transliteration": "uMeat",
        "englishLiteral": "and-hundred-of",
        "englishNatural": "and a hundred",
        "root": "meah",
        "morphology": {
          "type": "numeral"
        }
      },
      "context": {
        "hebrew": "חָמֵשׁ שָׁנִים **וּמְאַת** שָׁנָה וַיּוֹלֶד",
        "transliteration": "chamesh shanim **uMeat** shanah vaYoled",
        "englishLiteral": "five years **and-hundred-of** year, and-he-birthed",
        "englishNatural": "five years **and a hundred** years, and he birthed"
      }
    },
    {
      "location": {
        "book": "Genesis",
        "chapter": 5,
        "verse": 18
      },
      "wordIndex": 5,
      "sourceOrder": 5,
      "word": {
        "originalScript": "וּמְאַת",
        "transliteration": "uMeat",
        "englishLiteral": "and-hundred-of",
        "englishNatural": "and a hundred",
        "root": "meah",
        "morphology": {
          "type": "numeral"
        }
      },
      "context": {
        "hebrew": "וְשִׁשִּׁים שָׁנָה **וּמְאַת** שָׁנָה וַיּוֹלֶד",
        "transliteration": "veShishim shanah **uMeat** shanah vaYoled",
        "englishLiteral": "and-sixty year **and-hundred-of** year, and-he-birthed",
        "englishNatural": "and sixty years **and a hundred** years, and birthed"
      }
    },
    {
      "location": {
        "book": "Genesis",
        "chapter": 5,
        "verse": 25
      },
      "wordIndex": 5,
      "sourceOrder": 5,
      "word": {
        "originalScript": "וּמְאַת",
        "transliteration": "uMeat",
        "englishLiteral": "and-hundred",
        "englishNatural": "and a hundred",
        "root": "meah",
        "morphology": {
          "type": "numeral"
        }
      },
      "context": {
        "hebrew": "וּשְׁמֹנִים שָׁנָה **וּמְאַת** שָׁנָה וַיּוֹלֶד",
        "transliteration": "uShmonim shanah **uMeat** shanah vaYoled",
        "englishLiteral": "and-eighty year **and-hundred** year, and-birthed",
        "englishNatural": "and eighty years **and a hundred** years, and birthed"
      }
    },
    {
      "location": {
        "book": "Genesis",
        "chapter": 5,
        "verse": 28
      },
      "wordIndex": 5,
      "sourceOrder": 5,
      "word": {
        "originalScript": "וּמְאַת",
        "transliteration": "uMeat",
        "englishLiteral": "and-hundred",
        "englishNatural": "and a hundred",
        "root": "meah",
        "morphology": {
          "type": "numeral"
        }
      },
      "context": {
        "hebrew": "וּשְׁמֹנִים שָׁנָה **וּמְאַת** שָׁנָה וַיּוֹלֶד",
        "transliteration": "uShmonim shanah **uMeat** shanah vaYoled",
        "englishLiteral": "and-eighty year **and-hundred** year, and-birthed",
        "englishNatural": "and eighty years **and a hundred** years, and birthed"
      }
    }
  ]
}