{
  "key": "anokhi",
  "hebrew": "אנכי",
  "transliteration": "anokhi",
  "englishLiteral": "I",
  "englishNatural": "I",
  "type": "pronoun",
  "wordIndexes": {
    "exodus": {
      "3": {
        "6": [
          1
        ],
        "13": [
          5
        ]
      },
      "20": {
        "2": [
          0
        ],
        "5": [
          6
        ]
      }
    },
    "genesis": {
      "3": {
        "10": [
          8
        ]
      },
      "4": {
        "9": [
          12
        ]
      },
      "7": {
        "4": [
          4
        ]
      }
    },
    "isaiah": {
      "6": {
        "5": [
          9,
          14
        ]
      }
    },
    "jonah": {
      "1": {
        "9": [
          3
        ]
      },
      "3": {
        "2": [
          11
        ]
      }
    }
  },
  "usage": {},
  "translationConnections": []
}