{
  "root": "ra",
  "language": "hebrew",
  "occurrences": [
    {
      "location": {
        "book": "Genesis",
        "chapter": 2,
        "verse": 9
      },
      "wordIndex": 17,
      "word": {
        "originalScript": "וָרָע׃",
        "transliteration": "vaRa",
        "englishLiteral": "and-bad",
        "englishNatural": "and Bad",
        "root": "ra",
        "morphology": {
          "type": "adjective"
        }
      },
      "context": {
        "hebrew": "הַדַּעַת טוֹב **וָרָע׃**",
        "transliteration": "haDaat tov **vaRa**",
        "englishLiteral": "the-knowledge good **and-bad**",
        "englishNatural": "of Knowledge of Good **and Bad**"
      }
    },
    {
      "location": {
        "book": "Genesis",
        "chapter": 2,
        "verse": 17
      },
      "wordIndex": 3,
      "word": {
        "originalScript": "וָרָע",
        "transliteration": "vaRa",
        "englishLiteral": "and-bad",
        "englishNatural": "and Bad",
        "root": "ra",
        "morphology": {
          "type": "adjective"
        }
      },
      "context": {
        "hebrew": "הַדַּעַת טוֹב **וָרָע** לֹא תֹאכַל",
        "transliteration": "haDaat tov **vaRa** lo toAkhal",
        "englishLiteral": "the-knowledge good **and-bad** not you-will-eat",
        "englishNatural": "of Knowledge of Good **and Bad** not you will eat"
      }
    },
    {
      "location": {
        "book": "Genesis",
        "chapter": 3,
        "verse": 5
      },
      "wordIndex": 13,
      "word": {
        "originalScript": "וָרָע׃",
        "transliteration": "vaRa",
        "englishLiteral": "and-bad",
        "englishNatural": "and bad",
        "root": "ra",
        "morphology": {
          "type": "adjective"
        }
      },
      "context": {
        "hebrew": "יֹדְעֵי טוֹב **וָרָע׃**",
        "transliteration": "yodey tov **vaRa**",
        "englishLiteral": "knowing good **and-bad**",
        "englishNatural": "knowing good **and bad**"
      }
    },
    {
      "location": {
        "book": "Genesis",
        "chapter": 3,
        "verse": 22
      },
      "wordIndex": 10,
      "word": {
        "originalScript": "וָרָע",
        "transliteration": "vaRa",
        "englishLiteral": "and-bad",
        "englishNatural": "and bad",
        "root": "ra",
        "morphology": {
          "type": "adjective"
        }
      },
      "context": {
        "hebrew": "לָדַעַת טוֹב **וָרָע** וְעַתָּה פֶּן־",
        "transliteration": "laDaat tov **vaRa** veAtah pen-",
        "englishLiteral": "to-know good **and-bad** and-now or-else",
        "englishNatural": "to know good **and bad** and now or else"
      }
    },
    {
      "location": {
        "book": "Genesis",
        "chapter": 6,
        "verse": 5
      },
      "wordIndex": 12,
      "word": {
        "originalScript": "רַע",
        "transliteration": "ra",
        "englishLiteral": "bad",
        "englishNatural": "bad",
        "root": "ra",
        "morphology": {
          "type": "adjective"
        }
      },
      "context": {
        "hebrew": "לִבּוֹ רַק **רַע** כָּל־ הַיּוֹם",
        "transliteration": "libbo raq **ra** kol- haYom",
        "englishLiteral": "heart-his only **bad** all- the-day",
        "englishNatural": "his heart only **bad** all the day"
      }
    },
    {
      "location": {
        "book": "Genesis",
        "chapter": 8,
        "verse": 21
      },
      "wordIndex": 21,
      "word": {
        "originalScript": "רַע",
        "transliteration": "ra",
        "englishLiteral": "bad",
        "englishNatural": "bad",
        "root": "ra",
        "morphology": {
          "type": "adjective"
        }
      },
      "context": {
        "hebrew": "לֵב הָאָדָם **רַע** מִנְּעֻרָיו וְלֹא־",
        "transliteration": "lev haAdam **ra** miNeurav veLo-",
        "englishLiteral": "heart-of the-Earthling (Adam) **bad** from-his-youth and-not-",
        "englishNatural": "of the heart of the Earthling (Adam) **bad** from his youth not"
      }
    },
    {
      "location": {
        "book": "Job",
        "chapter": 1,
        "verse": 1
      },
      "wordIndex": 14,
      "word": {
        "originalScript": "מֵרָֽע",
        "transliteration": "meRa",
        "englishLiteral": "from-bad",
        "englishNatural": "from bad",
        "root": "ra",
        "morphology": {
          "type": "adjective"
        }
      },
      "context": {
        "hebrew": "אֱלֹהִ֖ים וְסָ֥ר **מֵרָֽע**",
        "transliteration": "Elohim veSar **meRa**",
        "englishLiteral": "Gods and-turning_aside **from-bad**",
        "englishNatural": "God and turning-aside **from bad**"
      }
    },
    {
      "location": {
        "book": "Psalms",
        "chapter": 23,
        "verse": 4
      },
      "wordIndex": 7,
      "word": {
        "originalScript": "רָע",
        "transliteration": "ra",
        "englishLiteral": "bad",
        "englishNatural": "bad",
        "root": "ra",
        "morphology": {
          "type": "noun"
        }
      },
      "context": {
        "hebrew": "לֹא־ אִירָא **רָע** כִּי־ אַתָּה",
        "transliteration": "lo- ira **ra** ki- atah",
        "englishLiteral": "not- I-fear **bad** that- you",
        "englishNatural": "not I fear **bad** that you"
      }
    },
    {
      "location": {
        "book": "Proverbs",
        "chapter": 22,
        "verse": 3
      },
      "wordIndex": 2,
      "word": {
        "originalScript": "רָעָה",
        "transliteration": "ra`ah",
        "englishLiteral": "bad",
        "englishNatural": "bad",
        "root": "ra",
        "morphology": {
          "type": "noun"
        }
      },
      "context": {
        "hebrew": "עָרוּם רָאָה **רָעָה** וְנִסְתָּר וּפְתָיִים",
        "transliteration": "arum ra'ah **ra`ah** veNiStar uFetayim",
        "englishLiteral": "Shrewd sees **bad** and-himself-hides but-simples",
        "englishNatural": "Shrewd sees **bad** and hides himself but the simple"
      }
    },
    {
      "location": {
        "book": "Jonah",
        "chapter": 1,
        "verse": 7
      },
      "wordIndex": 9,
      "word": {
        "originalScript": "הָרָעָה",
        "transliteration": "haRaah",
        "englishLiteral": "the-bad",
        "englishNatural": "this bad",
        "root": "ra",
        "morphology": {
          "type": "noun"
        }
      },
      "context": {
        "hebrew": "וְנֵדְעָה בְּשֶׁלְּמִי **הָרָעָה** הַזֹּאת לָנוּ",
        "transliteration": "veNedah beshelmi **haRaah** hazot lanu",
        "englishLiteral": "and-let-us-know for-whose-sake **the-bad** this to-us",
        "englishNatural": "and let us know for whose sake **this bad** is to us"
      }
    },
    {
      "location": {
        "book": "Jonah",
        "chapter": 1,
        "verse": 8
      },
      "wordIndex": 7,
      "word": {
        "originalScript": "הָרָעָה",
        "transliteration": "haRaah",
        "englishLiteral": "the-bad",
        "englishNatural": "the bad",
        "root": "ra",
        "morphology": {
          "type": "noun"
        }
      },
      "context": {
        "hebrew": "בַּאֲשֶׁר לְמִי־ **הָרָעָה** הַזֹּאת לָנוּ",
        "transliteration": "beAsher lemi- **haRaah** hazot lanu",
        "englishLiteral": "in-which for-who- **the-bad** this to-us",
        "englishNatural": "in which for who **the bad** this is to us"
      }
    },
    {
      "location": {
        "book": "Jonah",
        "chapter": 3,
        "verse": 8
      },
      "wordIndex": 11,
      "word": {
        "originalScript": "הָרָעָה",
        "transliteration": "haRaah",
        "englishLiteral": "the-bad",
        "englishNatural": "from the bad of",
        "root": "ra",
        "morphology": {
          "type": "adjective"
        }
      },
      "context": {
        "hebrew": "אִישׁ מִדַּרְכּוֹ **הָרָעָה** וּמִן־ הֶחָמָס",
        "transliteration": "ish midarko **haRaah** umin- heChamas",
        "englishLiteral": "man from-way-his **the-bad** and-from- the-violence",
        "englishNatural": "man his way **from the bad of** and from the violence"
      }
    },
    {
      "location": {
        "book": "Jonah",
        "chapter": 3,
        "verse": 10
      },
      "wordIndex": 7,
      "word": {
        "originalScript": "הָרָעָה",
        "transliteration": "haRaah",
        "englishLiteral": "the-bad",
        "englishNatural": "from the bad of",
        "root": "ra",
        "morphology": {
          "type": "adjective"
        }
      },
      "context": {
        "hebrew": "שָׁבוּ מִדַּרְכָּם **הָרָעָה** וַיִּנָּחֶם הָאֱלֹהִים",
        "transliteration": "shavu midarkam **haRaah** vaYinachem haElohim",
        "englishLiteral": "they-returned from-way-their **the-bad** and-comforted the-Gods",
        "englishNatural": "they returned their way **from the bad of** comforted and the God"
      }
    },
    {
      "location": {
        "book": "Jonah",
        "chapter": 3,
        "verse": 10
      },
      "wordIndex": 11,
      "word": {
        "originalScript": "הָרָעָה",
        "transliteration": "haRaah",
        "englishLiteral": "the-bad",
        "englishNatural": "the bad",
        "root": "ra",
        "morphology": {
          "type": "adjective"
        }
      },
      "context": {
        "hebrew": "הָאֱלֹהִים עַל־ **הָרָעָה** אֲשֶׁר־ דִּבֶּר",
        "transliteration": "haElohim al- **haRaah** asher- diber",
        "englishLiteral": "the-Gods over- **the-bad** which- he-spoke",
        "englishNatural": "and the God over **the bad** which he spoke"
      }
    },
    {
      "location": {
        "book": "Jonah",
        "chapter": 4,
        "verse": 1
      },
      "wordIndex": 3,
      "word": {
        "originalScript": "רָעָה",
        "transliteration": "raah",
        "englishLiteral": "bad",
        "englishNatural": "bad",
        "root": "ra",
        "morphology": {
          "type": "adjective"
        }
      },
      "context": {
        "hebrew": "אֶל־ יוֹנָה **רָעָה** גְדוֹלָה וַיִּחַר",
        "transliteration": "el- Yonah **raah** gedolah vaYichar",
        "englishLiteral": "to- Dove (Jonah) **bad** great and-fumed_angrily",
        "englishNatural": "to Dove (Jonah) **bad** a great and it fumed angrily"
      }
    },
    {
      "location": {
        "book": "Jonah",
        "chapter": 4,
        "verse": 2
      },
      "wordIndex": 31,
      "word": {
        "originalScript": "הָרָעָה",
        "transliteration": "haRaah",
        "englishLiteral": "the-bad",
        "englishNatural": "the bad",
        "root": "ra",
        "morphology": {
          "type": "adjective"
        }
      },
      "context": {
        "hebrew": "וְנִחָם עַל־ **הָרָעָה**",
        "transliteration": "veNicham al- **haRaah**",
        "englishLiteral": "and-comforting over- **the-bad**",
        "englishNatural": "and comforting over **the bad**"
      }
    },
    {
      "location": {
        "book": "Jonah",
        "chapter": 4,
        "verse": 6
      },
      "wordIndex": 13,
      "word": {
        "originalScript": "מֵרָעָתוֹ",
        "transliteration": "meRaato",
        "englishLiteral": "from-bad-his",
        "englishNatural": "from his bad",
        "root": "ra",
        "morphology": {
          "type": "noun"
        }
      },
      "context": {
        "hebrew": "לְהַצִּיל לוֹ **מֵרָעָתוֹ** וַיִּשְׂמַח יוֹנָה",
        "transliteration": "lehatzil lo **meRaato** vaYismach Yonah",
        "englishLiteral": "to-deliver to-him **from-bad-his** and-rejoiced Dove (Jonah)",
        "englishNatural": "to deliver to him **from his bad** rejoiced and Dove (Jonah)"
      }
    }
  ]
}